fairy/__init__.py
fairy/const.py
fairy/service.py
fairy/singleton.py
fairy/config/__init__.py
fairy/config/configparse.py
fairy/utils/__init__.py
fairy/utils/asyncs.py
fairy/utils/check.py
fairy/utils/db.py
fairy/utils/error.py
fairy/utils/log.py
fairy/utils/response.py
fairy/utils/sql_helper.py
fairy/utils/wrappers.py
fairy_tail-0.1.0.1.dist-info/METADATA
fairy_tail-0.1.0.1.dist-info/RECORD
fairy_tail-0.1.0.1.dist-info/WHEEL
fairy_tail-0.1.0.1.dist-info/top_level.txt
test/__init__.py
test/ocr.py
test/p.py
test/server_test.py
