Metadata-Version: 2.1
Name: fairy-tail
Version: 0.1.0.1
Summary: A small smart package
Home-page: https://github.com/BenjyHu/fairy
Author: BenjyHu
Author-email: m15227041551@163.com
License: MIT
Platform: UNKNOWN
Classifier: Programming Language :: Python :: 3
Classifier: License :: OSI Approved :: MIT License
Classifier: Operating System :: OS Independent
Requires-Python: >=3.6
Requires-Dist: flask
Requires-Dist: kazoo
Requires-Dist: pydantic
Requires-Dist: cached-property
Requires-Dist: pymysql
Requires-Dist: DBUtils
